ninja_schema/__init__.py
ninja_schema/compat.py
ninja_schema/errors.py
ninja_schema/py.typed
ninja_schema/types.py
ninja_schema/orm/__init__.py
ninja_schema/orm/factory.py
ninja_schema/orm/getters.py
ninja_schema/orm/mixins.py
ninja_schema/orm/model_schema.py
ninja_schema/orm/model_validators.py
ninja_schema/orm/schema.py
ninja_schema/orm/schema_registry.py
ninja_schema/orm/utils/__init__.py
ninja_schema/orm/utils/converter.py
ninja_schema/orm/utils/utils.py
ninja_schema/pydanticutils/__init__.py
ninja_schema-0.14.3.dist-info/licenses/LICENSE
ninja_schema-0.14.3.dist-info/WHEEL
ninja_schema-0.14.3.dist-info/METADATA
ninja_schema-0.14.3.dist-info/RECORD
